compilerM/__init__.py
compilerM/compiler.py
M_Language-0.1.dist-info/METADATA
M_Language-0.1.dist-info/WHEEL
M_Language-0.1.dist-info/top_level.txt
M_Language-0.1.dist-info/RECORD
