Metadata-Version: 2.1
Name: M-Language
Version: 0.1
Summary: MXB Language Beta Compiler
Home-page: https://github.com/hwan809/M-Language/
Author: Vivace
Author-email: hwan809@naver.com
License: MIT
Platform: UNKNOWN
Requires-Python: >=3
